<annotation>
	<folder>crumpled paper</folder>
	<filename>image.png</filename>
	<path>C:\Users\Crypt\Downloads\RecycleAI dataset\crumpled paper\image.png</path>
	<source>
		<database>Unknown</database>
	</source>
	<size>
		<width>216</width>
		<height>233</height>
		<depth>3</depth>
	</size>
	<segmented>0</segmented>
	<object>
		<name>crumpled paper</name>
		<pose>Unspecified</pose>
		<truncated>0</truncated>
		<difficult>0</difficult>
		<bndbox>
			<xmin>48</xmin>
			<ymin>34</ymin>
			<xmax>124</xmax>
			<ymax>118</ymax>
		</bndbox>
	</object>
	<object>
		<name>crumpled paper</name>
		<pose>Unspecified</pose>
		<truncated>0</truncated>
		<difficult>0</difficult>
		<bndbox>
			<xmin>83</xmin>
			<ymin>85</ymin>
			<xmax>193</xmax>
			<ymax>180</ymax>
		</bndbox>
	</object>
</annotation>
